{
  "tag": "巴基斯坦",
  "generated_at": "2026-05-28T23:17:45Z",
  "summary": [
    {
      "title": "巴基斯坦俾路支省客运列车遭恐怖袭击致47死 中方强烈谴责",
      "tags": [
        "军事",
        "恐怖袭击",
        "巴基斯坦",
        "中方表态"
      ],
      "summary": "5月24日，巴基斯坦俾路支省一列客运列车遭到爆炸袭击，导致重大人员伤亡。外交部发言人毛宁在25日的例行记者会上回应此事，表示中方强烈谴责此次恐怖袭击，对遇难者表示深切哀悼，向伤者和遇难者家属致以诚挚慰问。毛宁强调，中方坚决反对一切形式的恐怖主义，将继续坚定支持巴基斯坦打击恐怖主义、维护社会团结稳定和保护民众安全的努力。中方愿同巴方进一步加强反恐合作，共同维护地区的和平与安全。",
      "date": "2026-05-25"
    },
    {
      "title": "巴基斯坦一客运列车遭爆炸袭击 至少24人死亡数十人受伤",
      "tags": [
        "巴基斯坦",
        "列车爆炸",
        "恐怖袭击",
        "伤亡"
      ],
      "summary": "当地时间5月24日，巴基斯坦西南部俾路支省一列客运列车遭遇爆炸袭击。据当地警方消息，袭击已造成至少24人死亡、82人受伤。另有报道援引奎达市警官的话称，死亡人数已上升至27人，最终伤亡情况仍在进一步统计中。",
      "date": "2026-05-24"
    }
  ]
}
