{
  "tag": "美伊谈判",
  "generated_at": "2026-05-27T01:26:11Z",
  "summary": [
    {
      "title": "美伊谈判取得进展，特朗普称进展顺利，双方就资产解冻达成谅解",
      "tags": [
        "美伊谈判",
        "资产解冻",
        "外交",
        "伊朗",
        "美国"
      ],
      "summary": "美伊谈判取得进展，双方就解冻伊朗海外资产问题达成谅解。据伊朗塔斯尼姆通讯社26日报道，伊朗议长卡利巴夫在访问卡塔尔期间推动解冻伊朗240亿美元资金，伊方要求其中一半资金必须在美伊谅解备忘录发布后立即解冻，剩余部分在60天内解冻。卡塔尔半岛电视台25日报道，一名了解伊朗高级代表团在多哈会谈情况的消息人士表示，在卡塔尔斡旋下，美国与伊朗已就伊朗被冻结金融资产问题达成一项谅解，美伊双方可能于26日宣布达成协议。卡塔尔外交部一名官员当天向新华社记者证实，一个伊朗高级代表团正在多哈参加",
      "date": "2026-05-26"
    }
  ]
}
